mv_platform_observability/__init__.py
mv_platform_observability/decorator.py
mv_platform_observability/collectors/__init__.py
mv_platform_observability/collectors/metrics.py
mv_platform_observability/tracking/processing.py
mv_platform_observability-0.1.2.dist-info/METADATA
mv_platform_observability-0.1.2.dist-info/WHEEL
mv_platform_observability-0.1.2.dist-info/RECORD
