Metadata-Version: 2.4
Name: mv-platform-observability
Version: 0.1.2
Summary: Add your description here
Author-email: Ruslan_Mendybayev <ruslan_mendybayev@epam.com>
Requires-Python: >=3.10
Requires-Dist: azure-eventhub>=5.14.0
Requires-Dist: azure-identity>=1.20.0
Requires-Dist: mv-platform-core
Requires-Dist: pydantic>=2.10.6
Requires-Dist: requests>=2.32.3
